arxivchecker.py
arxiv_checker-1.4.4.dist-info/DESCRIPTION.rst
arxiv_checker-1.4.4.dist-info/METADATA
arxiv_checker-1.4.4.dist-info/RECORD
arxiv_checker-1.4.4.dist-info/WHEEL
arxiv_checker-1.4.4.dist-info/metadata.json
arxiv_checker-1.4.4.dist-info/top_level.txt
