Metadata-Version: 2.0
Name: arxiv-checker
Version: 1.4.4
Summary: Cross check the most recent arxiv mailing against a list of authors.
Home-page: https://github.com/adamdempsey90/arxiv-checker
Author: Adam M. Dempsey
Author-email: adamdemps@gmail.com
License: MIT
Keywords: arXiv science research journal
Platform: UNKNOWN
Classifier: Development Status :: 5 - Production/Stable
Classifier: Intended Audience :: Science/Research
Classifier: Topic :: Scientific/Engineering
Classifier: Topic :: Scientific/Engineering :: Physics
Classifier: Topic :: Scientific/Engineering :: Mathematics
Classifier: Topic :: Scientific/Engineering :: Astronomy
Classifier: License :: OSI Approved :: MIT License
Classifier: Programming Language :: Python :: 2.7
Classifier: Programming Language :: Python :: 3.5
Requires-Dist: bs4
Requires-Dist: requests
